flakehell/__init__.py
flakehell/__main__.py
flakehell/_cli.py
flakehell/_constants.py
flakehell/_types.py
flakehell/_version.py
flakehell/_logic/__init__.py
flakehell/_logic/_baseline.py
flakehell/_logic/_colors.py
flakehell/_logic/_config.py
flakehell/_logic/_discover.py
flakehell/_logic/_extractors.py
flakehell/_logic/_plugin.py
flakehell/_logic/_snapshot.py
flakehell/_patched/__init__.py
flakehell/_patched/_app.py
flakehell/_patched/_checkers.py
flakehell/_patched/_plugins.py
flakehell/_patched/_processor.py
flakehell/_patched/_style_guide.py
flakehell/_patched/_violation.py
flakehell/commands/__init__.py
flakehell/commands/_baseline.py
flakehell/commands/_code.py
flakehell/commands/_codes.py
flakehell/commands/_lint.py
flakehell/commands/_missed.py
flakehell/commands/_plugins.py
flakehell/commands/_version.py
flakehell/formatters/__init__.py
flakehell/formatters/_baseline.py
flakehell/formatters/_colored.py
flakehell/formatters/_gitlab.py
flakehell/formatters/_grouped.py
flakehell/formatters/_json.py
flakehell/formatters/_stat.py
flakehell/parsers/__init__.py
flakehell/parsers/_base.py
flakehell/parsers/_jupyter.py
flakehell/parsers/_markdown.py
flakehell/parsers/_python.py
flakehell/parsers/_rst.py
flakehell/parsers/_yaml.py
flakehell/plugins/__init__.py
flakehell/plugins/_pylint.py
ezflakehell-0.9.2.dist-info/entry_points.txt
ezflakehell-0.9.2.dist-info/LICENSE
ezflakehell-0.9.2.dist-info/WHEEL
ezflakehell-0.9.2.dist-info/METADATA
ezflakehell-0.9.2.dist-info/RECORD
